Metadata-Version: 2.1
Name: easy_fastapi
Version: 0.13.1
Summary: 基于 FastAPI 开发的后端框架，集成了 Tortoise ORM、Pydantic、Aerich、PyJWT、PyYAML、Redis 等插件，并且可以在编写好 `models` 文件后执行 `manager.py gen` 命令，批量生成 `schemas`、`routers`、`services` 代码，旨在提供一个高效、易用的后端开发环境。该框架通过清晰的目录结构和模块化设计，大大减少了项目的前期开发工作，帮助开发者快速构建和部署后端服务。
Home-page: https://github.com/one-ccs/easy_fastapi
Author: one-ccs
Author-email: one-ccs@foxmal.com
License: MIT
Classifier: Development Status :: 3 - Alpha
Classifier: Intended Audience :: Developers
Classifier: Topic :: Software Development :: Build Tools
Classifier: License :: OSI Approved :: MIT License
Classifier: Programming Language :: Python :: 3
Requires-Python: >=3.10
License-File: LICENSE
Requires-Dist: easy-pyoc>=0.9.1
Requires-Dist: fastapi>=0.115.4
Requires-Dist: tortoise-orm>=0.21.7
Requires-Dist: pydantic>=2.10.6
Requires-Dist: aerich>=0.7.2
Requires-Dist: pyjwt>=2.9.0
Requires-Dist: pyyaml>=6.0.2
Requires-Dist: redis>=5.2.0
Requires-Dist: bcrypt>=4.2.0
